.gitignore
AUTHORS
ChangeLog
LICENSE
MANIFEST.in
README.rst
setup.py
hpcloud_auth_openstack/__init__.py
hpcloud_auth_openstack/plugin.py
hpcloud_auth_openstack.egg-info/PKG-INFO
hpcloud_auth_openstack.egg-info/SOURCES.txt
hpcloud_auth_openstack.egg-info/dependency_links.txt
hpcloud_auth_openstack.egg-info/entry_points.txt
hpcloud_auth_openstack.egg-info/top_level.txt