Metadata-Version: 1.1
Name: hpcloud-auth-openstack
Version: 1.0
Summary: HP Cloud Auth Plugin for OpenStack Clients.
Home-page: https://github.com/emonty/hpcloud-auth-openstack
Author: OpenStack
Author-email: openstack-dev@lists.openstack.org
License: Apache License, Version 2.0
Platform: UNKNOWN
Classifier: Development Status :: 5 - Production/Stable
Classifier: Environment :: Console
Classifier: Intended Audience :: Developers
Classifier: Intended Audience :: Information Technology
Classifier: License :: OSI Approved :: Apache Software License
Classifier: Operating System :: OS Independent
Classifier: Programming Language :: Python
